Pyfrontier/__init__.py
Pyfrontier/domain/__init__.py
Pyfrontier/domain/assurance_region.py
Pyfrontier/domain/dmu.py
Pyfrontier/domain/metrics.py
Pyfrontier/domain/parallel.py
Pyfrontier/domain/result.py
Pyfrontier/domain/slack_weight.py
Pyfrontier/frontier_model/__init__.py
Pyfrontier/frontier_model/_additive_dea.py
Pyfrontier/frontier_model/_base.py
Pyfrontier/frontier_model/_dea.py
Pyfrontier/frontier_model/_hierarchical_dea.py
Pyfrontier/solver/__init__.py
Pyfrontier/solver/_additive_solver.py
Pyfrontier/solver/_base.py
Pyfrontier/solver/_envelope_solver.py
Pyfrontier/solver/_models.py
Pyfrontier/solver/_multiple_solver.py
Pyfrontier-1.0.2.dist-info/LICENSE
Pyfrontier-1.0.2.dist-info/METADATA
Pyfrontier-1.0.2.dist-info/WHEEL
Pyfrontier-1.0.2.dist-info/top_level.txt
Pyfrontier-1.0.2.dist-info/RECORD
