Metadata-Version: 2.1
Name: Pyfrontier
Version: 1.0.2
Summary: Pyfrontier is a data envelopment analysis for Python user.
Home-page: https://nibutake.github.io/PyDEA/index.html?
Download-URL: https://github.com/NibuTake/PyDEA
Author: Takeshi Morinibu
Author-email: takeshi715tech@gmail.com
License: MIT
Classifier: Intended Audience :: Science/Research
Classifier: License :: OSI Approved :: MIT License
Classifier: Programming Language :: Python :: 3
Classifier: Programming Language :: Python :: 3.8
Classifier: Programming Language :: Python :: 3.9
Classifier: Programming Language :: Python :: 3.10
Classifier: Programming Language :: Python :: 3.11
Classifier: Programming Language :: Python :: 3 :: Only
Classifier: Topic :: Scientific/Engineering
Classifier: Topic :: Scientific/Engineering :: Mathematics
Classifier: Topic :: Software Development
Classifier: Topic :: Software Development :: Libraries
Requires-Python: >=3.8
License-File: LICENSE
Requires-Dist: numpy >=1.21
Requires-Dist: pulp >=2.6.0
